LICENSE
MANIFEST.in
README.md
setup.cfg
setup.py
concierge_paas_plugin/__init__.py
concierge_paas_plugin/admin.py
concierge_paas_plugin/api.py
concierge_paas_plugin/apps.py
concierge_paas_plugin/dev_settings.py
concierge_paas_plugin/forms.py
concierge_paas_plugin/models.py
concierge_paas_plugin/settings.py
concierge_paas_plugin/tests.py
concierge_paas_plugin/urls.py
concierge_paas_plugin/views.py
concierge_paas_plugin.egg-info/PKG-INFO
concierge_paas_plugin.egg-info/SOURCES.txt
concierge_paas_plugin.egg-info/dependency_links.txt
concierge_paas_plugin.egg-info/requires.txt
concierge_paas_plugin.egg-info/top_level.txt
concierge_paas_plugin/helper/__init__.py
concierge_paas_plugin/helper/graphql_mutation.py
concierge_paas_plugin/helper/graphql_post.py
concierge_paas_plugin/helper/graphql_query.py
concierge_paas_plugin/helper/model_configuration.py
concierge_paas_plugin/migrations/0001_initial.py
concierge_paas_plugin/migrations/0002_user.py
concierge_paas_plugin/migrations/0003_delete_user.py
concierge_paas_plugin/migrations/__init__.py
concierge_paas_plugin/tests/__init__.py
concierge_paas_plugin/tests/testrunner.py
concierge_paas_plugin/tests/testssettings.py
concierge_paas_plugin/tests/tests_integration/__init__.py
concierge_paas_plugin/tests/tests_integration/conftest.py
concierge_paas_plugin/tests/tests_integration/test_configuration.py
concierge_paas_plugin/tests/tests_integration/test_graphqlcore.py
concierge_paas_plugin/tests/tests_nodb/__init__.py
concierge_paas_plugin/tests/tests_nodb/conftest.py